cidre/__init__.py
cidre/cli.py
cidre/countries.py
cidre/cidrs/__init__.py
cidre/cidrs/cidr_counter.py
cidre/cidrs/cidr_store.py
cidre/cidrs/rir_fetcher.py
cidre/firewalls/__init__.py
cidre/firewalls/iptables_firewall.py
cidre/firewalls/ufw_firewall.py
cidre_cli-2.1.3.dist-info/LICENSE
cidre_cli-2.1.3.dist-info/METADATA
cidre_cli-2.1.3.dist-info/WHEEL
cidre_cli-2.1.3.dist-info/entry_points.txt
cidre_cli-2.1.3.dist-info/top_level.txt
cidre_cli-2.1.3.dist-info/RECORD
