Metadata-Version: 2.1
Name: cidre-cli
Version: 2.1.3
Summary: A CLI tool for fetching and managing CIDR IP ranges from RIRs with firewall integration.
Home-page: https://github.com/vulnebify/cidre
Author: Alex @ Vulnebify
Author-email: contact.pypi@vulnebify.com
Classifier: Programming Language :: Python :: 3
Classifier: License :: OSI Approved :: MIT License
Classifier: Operating System :: OS Independent
Requires-Python: >=3.6
License-File: LICENSE
Requires-Dist: netaddr==1.3.0
Requires-Dist: requests==2.32.4
